setup.py
distributions_raco/Binomialdistribution.py
distributions_raco/Gaussiandistribution.py
distributions_raco/Generaldistribution.py
distributions_raco/__init__.py
distributions_raco.egg-info/PKG-INFO
distributions_raco.egg-info/SOURCES.txt
distributions_raco.egg-info/dependency_links.txt
distributions_raco.egg-info/not-zip-safe
distributions_raco.egg-info/top_level.txt