Metadata-Version: 1.0
Name: distributions-raco
Version: 0.1
Summary: Gaussian distributions de raco
Home-page: UNKNOWN
Author: UNKNOWN
Author-email: UNKNOWN
License: UNKNOWN
Platform: UNKNOWN
